MANIFEST.in
README.rst
setup.cfg
setup.py
docs/Makefile
docs/alternatives.rst
docs/conf.py
docs/contribute.rst
docs/exts.py
docs/index.rst
docs/installation.rst
docs/license.rst
docs/make.bat
docs/quickstart.rst
docs/requirements.txt
docs/api/cli.rst
docs/api/conf.settings.rst
docs/api/index.rst
docs/api/nodes.rst
docs/api/backends/git.rst
docs/api/backends/hg.rst
docs/api/backends/index.rst
docs/api/utils/index.rst
docs/theme/ADC/layout.html
docs/theme/ADC/theme.conf
docs/theme/ADC/static/adctheme.css
docs/theme/ADC/static/breadcrumb_background.png
docs/theme/ADC/static/documentation.png
docs/theme/ADC/static/header_sm_mid.png
docs/theme/ADC/static/mobile.css
docs/theme/ADC/static/scrn1.png
docs/theme/ADC/static/scrn2.png
docs/theme/ADC/static/searchfield_leftcap.png
docs/theme/ADC/static/searchfield_repeat.png
docs/theme/ADC/static/searchfield_rightcap.png
docs/theme/ADC/static/title_background.png
docs/theme/ADC/static/toc.js
docs/theme/ADC/static/triangle_closed.png
docs/theme/ADC/static/triangle_left.png
docs/theme/ADC/static/triangle_open.png
docs/usage/index.rst
docs/usage/vcsrc.rst
vcs/__init__.py
vcs/__init__.pyc
vcs/cli.py
vcs/cli.pyc
vcs/exceptions.py
vcs/exceptions.pyc
vcs/extras.py
vcs/extras.pyc
vcs/nodes.py
vcs/subprocessio.py
vcs.latest.egg-info/PKG-INFO
vcs.latest.egg-info/SOURCES.txt
vcs.latest.egg-info/dependency_links.txt
vcs.latest.egg-info/entry_points.txt
vcs.latest.egg-info/not-zip-safe
vcs.latest.egg-info/requires.txt
vcs.latest.egg-info/top_level.txt
vcs/backends/__init__.py
vcs/backends/__init__.pyc
vcs/backends/base.py
vcs/backends/base.pyc
vcs/backends/git/__init__.py
vcs/backends/git/__init__.pyc
vcs/backends/git/changeset.py
vcs/backends/git/config.py
vcs/backends/git/inmemory.py
vcs/backends/git/repository.py
vcs/backends/git/repository.pyc
vcs/backends/git/workdir.py
vcs/backends/hg/__init__.py
vcs/backends/hg/__init__.pyc
vcs/backends/hg/changeset.py
vcs/backends/hg/inmemory.py
vcs/backends/hg/repository.py
vcs/backends/hg/repository.pyc
vcs/backends/hg/workdir.py
vcs/commands/__init__.py
vcs/commands/cat.py
vcs/commands/completion.py
vcs/commands/log.py
vcs/commands/standup.py
vcs/commands/summary.py
vcs/conf/__init__.py
vcs/conf/__init__.pyc
vcs/conf/settings.py
