Metadata-Version: 1.1
Name: vcs.latest
Version: 0.5.1
Summary: UNKNOWN
Home-page: https://github.com/codeinn/vcs
Author: Marcin Kuzminski, Lukasz Balcerzak
Author-email: marcin@python-works.com
License: UNKNOWN
Platform: UNKNOWN
Classifier: Development Status :: 4 - Beta
Classifier: License :: OSI Approved :: MIT License
Classifier: Intended Audience :: Developers
Classifier: Programming Language :: Python
Classifier: Operating System :: OS Independent
